{
  "button": {
    "color": {
      "primary": {
        "default": {
          "bg": {
            "value": "{semantic.accent.default}",
            "type": "color"
          }
        },
        "hover": {
          "bg": {
            "value": "{semantic.accent.default}",
            "type": "color"
          }
        },
        "active": {
          "bg": {
            "value": "{semantic.accent.default}",
            "type": "color"
          }
        },
        "focus": {
          "bg": {
            "value": "{semantic.accent.default}",
            "type": "color"
          }
        }
      }
    },
    "sm": {
      "height": {
        "value": "{sizing.default} * 1.5",
        "type": "sizing"
      }
    },
    "md": {
      "height": {
        "value": "{sizing.default} * 4",
        "type": "sizing"
      }
    },
    "lg": {
      "height": {
        "value": "{sizing.default} * 2.5",
        "type": "sizing"
      }
    }
  }
}