{
  "component": {
    "avatar": {
      "color": {
        "solid": {
          "bg": {
            "default": {
              "$value": "{app.color.component.primary.bg.solid.default}",
              "$type": "color"
            }
          },
          "border": {
            "default": {
              "$value": "transparent",
              "$type": "color"
            }
          },
          "fg": {
            "default": {
              "$value": "{app.color.component.primary.fg.onSolid.default}",
              "$type": "color"
            }
          }
        },
        "outline": {
          "bg": {
            "default": {
              "$value": "transparent",
              "$type": "color"
            }
          },
          "border": {
            "default": {
              "$value": "{app.color.component.primary.border.translucent.default}",
              "$type": "color"
            }
          },
          "fg": {
            "default": {
              "$value": "{app.color.component.primary.fg.solid.default}",
              "$type": "color"
            }
          }
        }
      },
      "dimension": {
        "width": {
          "xs": {
            "default": {
              "$value": "{component.avatar.dimension.height.xs.default}",
              "$type": "dimension"
            },
            "inline": {
              "$value": "{component.avatar.dimension.width.xs.default} - 0.5rem",
              "$type": "dimension"
            }
          },
          "sm": {
            "default": {
              "$value": "{component.avatar.dimension.height.sm.default}",
              "$type": "dimension"
            },
            "inline": {
              "$value": "{component.avatar.dimension.width.sm.default} - 0.5rem",
              "$type": "dimension"
            }
          },
          "md": {
            "default": {
              "$value": "{component.avatar.dimension.height.md.default}",
              "$type": "dimension"
            },
            "inline": {
              "$value": "{component.avatar.dimension.width.md.default} - 0.5rem",
              "$type": "dimension"
            }
          },
          "lg": {
            "default": {
              "$value": "{component.avatar.dimension.height.lg.default}",
              "$type": "dimension"
            },
            "inline": {
              "$value": "{component.avatar.dimension.width.lg.default} - 0.5rem",
              "$type": "dimension"
            }
          },
          "xl": {
            "default": {
              "$value": "{component.avatar.dimension.height.xl.default}",
              "$type": "dimension"
            },
            "inline": {
              "$value": "{component.avatar.dimension.width.xl.default} - 0.5rem",
              "$type": "dimension"
            }
          }
        },
        "height": {
          "xs": {
            "default": {
              "$value": "{component.avatar.dimension.height.sm.default} - 0.5rem",
              "$type": "dimension"
            },
            "inline": {
              "$value": "{component.avatar.dimension.height.xs.default} - 0.5rem",
              "$type": "dimension"
            }
          },
          "sm": {
            "default": {
              "$value": "{component.avatar.dimension.height.md.default} - 0.5rem",
              "$type": "dimension"
            },
            "inline": {
              "$value": "{app.dimension.component.height.lg} - 0.5rem",
              "$type": "dimension"
            }
          },
          "md": {
            "default": {
              "$value": "{app.dimension.component.height.xl}",
              "$type": "dimension"
            },
            "inline": {
              "$value": "{component.avatar.dimension.height.md.default} - 0.5rem",
              "$type": "dimension"
            }
          },
          "lg": {
            "default": {
              "$value": "{component.avatar.dimension.height.md.default} + 0.5rem",
              "$type": "dimension"
            },
            "inline": {
              "$value": "{component.avatar.dimension.height.lg.default} - 0.5rem",
              "$type": "dimension"
            }
          },
          "xl": {
            "default": {
              "$value": "{component.avatar.dimension.height.lg.default} + 0.5rem",
              "$type": "dimension"
            },
            "inline": {
              "$value": "{component.avatar.dimension.height.xl.default} - 0.5rem",
              "$type": "dimension"
            }
          }
        },
        "radius": {
          "xs": {
            "default": {
              "$value": "{component.avatar.dimension.radius.sm.default} - 0.125rem",
              "$type": "dimension"
            },
            "inline": {
              "$value": "{component.avatar.dimension.radius.xs.default} - 0.25rem",
              "$type": "dimension"
            }
          },
          "sm": {
            "default": {
              "$value": "{component.avatar.dimension.radius.md.default} - 0.125rem",
              "$type": "dimension"
            },
            "inline": {
              "$value": "{component.avatar.dimension.radius.sm.default} - 0.25rem",
              "$type": "dimension"
            }
          },
          "md": {
            "default": {
              "$value": "1rem",
              "$type": "dimension"
            },
            "inline": {
              "$value": "{component.avatar.dimension.radius.md.default} - 0.125rem",
              "$type": "dimension"
            }
          },
          "lg": {
            "default": {
              "$value": "{component.avatar.dimension.radius.md.default} + 0.125rem",
              "$type": "dimension"
            },
            "inline": {
              "$value": "{component.avatar.dimension.radius.lg.default} - 0.125rem",
              "$type": "dimension"
            }
          },
          "xl": {
            "default": {
              "$value": "{component.avatar.dimension.radius.lg.default} + 0.125rem",
              "$type": "dimension"
            },
            "inline": {
              "$value": "{component.avatar.dimension.radius.xl.default} - 0.125rem",
              "$type": "dimension"
            }
          }
        },
        "border": {
          "default": {
            "$value": "{app.dimension.component.border.default}",
            "$type": "dimension"
          }
        },
        "symbol": {
          "xs": {
            "default": {
              "$value": "{component.avatar.fontSize.xs.symbol.default}",
              "$type": "dimension"
            },
            "inline": {
              "$value": "{component.avatar.fontSize.xs.symbol.inline}",
              "$type": "dimension"
            }
          },
          "sm": {
            "default": {
              "$value": "{component.avatar.fontSize.sm.symbol.default}",
              "$type": "dimension"
            },
            "inline": {
              "$value": "{component.avatar.fontSize.sm.symbol.inline}",
              "$type": "dimension"
            }
          },
          "md": {
            "default": {
              "$value": "{component.avatar.fontSize.md.symbol.default}",
              "$type": "dimension"
            },
            "inline": {
              "$value": "{component.avatar.fontSize.md.symbol.inline}",
              "$type": "dimension"
            }
          },
          "lg": {
            "default": {
              "$value": "{component.avatar.fontSize.lg.symbol.default}",
              "$type": "dimension"
            },
            "inline": {
              "$value": "{component.avatar.fontSize.lg.symbol.inline}",
              "$type": "dimension"
            }
          },
          "xl": {
            "default": {
              "$value": "{component.avatar.fontSize.xl.symbol.default}",
              "$type": "dimension"
            },
            "inline": {
              "$value": "{component.avatar.fontSize.xl.symbol.inline}",
              "$type": "dimension"
            }
          }
        }
      },
      "fontFamily": {
        "default": {
          "$value": "{app.fontFamily.component.number}",
          "$type": "fontFamilies"
        },
        "icon": {
          "$value": "{app.fontFamily.component.symbol}",
          "$type": "fontFamilies"
        }
      },
      "fontWeight": {
        "default": {
          "$value": "{app.fontWeight.component.text.strong}",
          "$type": "fontWeights"
        }
      },
      "lineHeight": {
        "default": {
          "$value": "{app.lineHeight.none}",
          "$type": "lineHeights"
        }
      },
      "fontSize": {
        "xs": {
          "default": {
            "$value": "{component.avatar.fontSize.sm.default} - 0.125rem",
            "$type": "fontSizes"
          },
          "inline": {
            "$value": "{component.avatar.fontSize.xs.default} - 0.25rem",
            "$type": "fontSizes"
          },
          "symbol": {
            "default": {
              "$value": "{component.avatar.fontSize.xs.default} * 1.5",
              "$type": "fontSizes"
            },
            "inline": {
              "$value": "{component.avatar.fontSize.xs.symbol.default} - 0.25rem",
              "$type": "fontSizes"
            }
          }
        },
        "sm": {
          "default": {
            "$value": "{component.avatar.fontSize.md.default} - 0.125rem",
            "$type": "fontSizes"
          },
          "inline": {
            "$value": "{component.avatar.fontSize.sm.default} - 0.25rem",
            "$type": "fontSizes"
          },
          "symbol": {
            "default": {
              "$value": "{component.avatar.fontSize.sm.default} * 1.5",
              "$type": "fontSizes"
            },
            "inline": {
              "$value": "{component.avatar.fontSize.sm.symbol.default} - 0.25rem",
              "$type": "fontSizes"
            }
          }
        },
        "md": {
          "default": {
            "$value": "{app.fontSize.component.text.xl}",
            "$type": "fontSizes"
          },
          "inline": {
            "$value": "{component.avatar.fontSize.md.default} - 0.25rem",
            "$type": "fontSizes"
          },
          "symbol": {
            "default": {
              "$value": "{component.avatar.fontSize.md.default} * 1.5",
              "$type": "fontSizes"
            },
            "inline": {
              "$value": "{component.avatar.fontSize.md.symbol.default} - 0.25rem",
              "$type": "fontSizes"
            }
          }
        },
        "lg": {
          "default": {
            "$value": "{component.avatar.fontSize.md.default} + 0.125rem",
            "$type": "fontSizes"
          },
          "inline": {
            "$value": "{component.avatar.fontSize.lg.default} - 0.25rem",
            "$type": "fontSizes"
          },
          "symbol": {
            "default": {
              "$value": "{component.avatar.fontSize.lg.default} * 1.5",
              "$type": "fontSizes"
            },
            "inline": {
              "$value": "{component.avatar.fontSize.lg.symbol.default} - 0.25rem",
              "$type": "fontSizes"
            }
          }
        },
        "xl": {
          "default": {
            "$value": "{component.avatar.fontSize.lg.default} + 0.125rem",
            "$type": "fontSizes"
          },
          "inline": {
            "$value": "{component.avatar.fontSize.xl.default} - 0.25rem",
            "$type": "fontSizes"
          },
          "symbol": {
            "default": {
              "$value": "{component.avatar.fontSize.xl.default} * 1.5",
              "$type": "fontSizes"
            },
            "inline": {
              "$value": "{component.avatar.fontSize.xl.symbol.default} - 0.25rem",
              "$type": "fontSizes"
            }
          }
        }
      },
      "letterSpacing": {
        "default": {
          "$value": "2%",
          "$type": "letterSpacing"
        }
      },
      "textCase": {
        "default": {
          "$value": "{app.textCase.component.default}",
          "$type": "textCase"
        }
      }
    }
  }
}
