{
  "component": {
    "menuItem": {
      "color": {
        "accent": {
          "ghost": {
            "bg": {
              "default": {
                "value": "transparent",
                "type": "color"
              },
              "hover": {
                "value": "{app.color.component.accent.bg.translucent}",
                "type": "color",
                "$extensions": {
                  "studio.tokens": {
                    "modify": {
                      "type": "alpha",
                      "value": "{config.color.accent.alpha.bg.hover}",
                      "space": "hsl"
                    }
                  }
                }
              },
              "active": {
                "value": "{app.color.component.accent.bg.translucent}",
                "type": "color",
                "$extensions": {
                  "studio.tokens": {
                    "modify": {
                      "type": "alpha",
                      "value": "{config.color.accent.alpha.bg.active}",
                      "space": "hsl"
                    }
                  }
                }
              }
            },
            "fg": {
              "default": {
                "value": "{app.color.component.accent.fg.onTranslucent}",
                "type": "color"
              }
            }
          },
          "plain": {
            "fg": {
              "default": {
                "value": "{app.color.component.accent.fg.solid}",
                "type": "color"
              },
              "hover": {
                "value": "{app.color.component.accent.fg.solid}",
                "type": "color",
                "$extensions": {
                  "studio.tokens": {
                    "modify": {
                      "type": "darken",
                      "value": "{config.color.accent.darken.hover}",
                      "space": "hsl"
                    }
                  }
                }
              },
              "active": {
                "value": "{app.color.component.accent.fg.solid}",
                "type": "color",
                "$extensions": {
                  "studio.tokens": {
                    "modify": {
                      "type": "darken",
                      "value": "{config.color.accent.darken.active}",
                      "space": "hsl"
                    }
                  }
                }
              }
            }
          }
        },
        "primary": {
          "ghost": {
            "bg": {
              "default": {
                "value": "transparent",
                "type": "color"
              },
              "hover": {
                "value": "{app.color.component.primary.bg.translucent}",
                "type": "color",
                "$extensions": {
                  "studio.tokens": {
                    "modify": {
                      "type": "alpha",
                      "value": "0.05",
                      "space": "hsl"
                    }
                  }
                }
              },
              "active": {
                "value": "{app.color.component.primary.bg.translucent}",
                "type": "color",
                "$extensions": {
                  "studio.tokens": {
                    "modify": {
                      "type": "alpha",
                      "value": "{config.color.grey.alpha.bg.active}",
                      "space": "hsl"
                    }
                  }
                }
              }
            },
            "fg": {
              "command": {
                "default": {
                  "value": "{app.color.surface.fg.muted}",
                  "type": "color"
                },
                "hover": {
                  "value": "{app.color.component.primary.fg.onTranslucent}",
                  "type": "color"
                }
              },
              "label": {
                "default": {
                  "value": "{app.color.component.primary.fg.onTranslucent}",
                  "type": "color"
                }
              }
            }
          },
          "plain": {
            "fg": {
              "label": {
                "default": {
                  "value": "{app.color.component.primary.fg.solid}",
                  "type": "color"
                },
                "hover": {
                  "value": "{app.color.component.primary.fg.solid}",
                  "type": "color",
                  "$extensions": {
                    "studio.tokens": {
                      "modify": {
                        "type": "darken",
                        "value": "{config.color.grey.darken.hover}",
                        "space": "hsl"
                      }
                    }
                  }
                },
                "active": {
                  "value": "{app.color.component.primary.fg.solid}",
                  "type": "color",
                  "$extensions": {
                    "studio.tokens": {
                      "modify": {
                        "type": "darken",
                        "value": "{config.color.grey.darken.active}",
                        "space": "hsl"
                      }
                    }
                  }
                }
              }
            }
          }
        },
        "danger": {
          "ghost": {
            "bg": {
              "default": {
                "value": "transparent",
                "type": "color"
              },
              "hover": {
                "value": "{app.color.component.danger.bg.translucent}",
                "type": "color",
                "$extensions": {
                  "studio.tokens": {
                    "modify": {
                      "type": "alpha",
                      "value": "{config.color.danger.alpha.bg.hover}",
                      "space": "hsl"
                    }
                  }
                }
              },
              "active": {
                "value": "{app.color.component.danger.bg.translucent}",
                "type": "color",
                "$extensions": {
                  "studio.tokens": {
                    "modify": {
                      "type": "alpha",
                      "value": "{config.color.danger.alpha.bg.active}",
                      "space": "hsl"
                    }
                  }
                }
              }
            },
            "fg": {
              "default": {
                "value": "{app.color.component.danger.fg.onTranslucent}",
                "type": "color"
              }
            }
          },
          "plain": {
            "fg": {
              "default": {
                "value": "{app.color.component.danger.fg.solid}",
                "type": "color"
              },
              "hover": {
                "value": "{app.color.component.danger.fg.solid}",
                "type": "color",
                "$extensions": {
                  "studio.tokens": {
                    "modify": {
                      "type": "darken",
                      "value": "{config.color.danger.darken.hover}",
                      "space": "hsl"
                    }
                  }
                }
              },
              "active": {
                "value": "{app.color.component.danger.fg.solid}",
                "type": "color",
                "$extensions": {
                  "studio.tokens": {
                    "modify": {
                      "type": "darken",
                      "value": "{config.color.danger.darken.active}",
                      "space": "hsl"
                    }
                  }
                }
              }
            }
          }
        },
        "disabled": {
          "ghost": {
            "bg": {
              "default": {
                "value": "transparent",
                "type": "color"
              }
            },
            "fg": {
              "default": {
                "value": "{app.color.component.disabled.fg.solid}",
                "type": "color"
              }
            }
          },
          "plain": {
            "fg": {
              "default": {
                "value": "{app.color.component.disabled.fg.solid}",
                "type": "color"
              }
            }
          }
        },
        "focus": {
          "border": {
            "default": {
              "value": "{app.color.component.focus.border.default}",
              "type": "color"
            }
          }
        }
      },
      "typography": {
        "text": {
          "value": "{app.typography.control.text.default}",
          "type": "typography"
        },
        "symbol": {
          "value": "{app.typography.control.symbol.default}",
          "type": "typography"
        }
      },
      "dimension": {
        "height": {
          "sm": {
            "value": "{app.dimension.control.height.sm}",
            "type": "dimension"
          },
          "md": {
            "value": "{app.dimension.control.height.md}",
            "type": "dimension"
          },
          "lg": {
            "value": "{app.dimension.control.height.lg}",
            "type": "dimension"
          }
        },
        "padding": {
          "sm": {
            "value": "{app.dimension.control.padding.sm}",
            "type": "dimension"
          },
          "md": {
            "value": "{app.dimension.control.padding.md}",
            "type": "dimension"
          },
          "lg": {
            "value": "{app.dimension.control.padding.lg}",
            "type": "dimension"
          },
          "label": {
            "value": "4px",
            "type": "dimension"
          }
        },
        "gap": {
          "sm": {
            "value": "{component.menuItem.dimension.gap.md} - {component.menuItem.config.gap.step}",
            "type": "dimension"
          },
          "md": {
            "value": "{component.menuItem.config.gap.default}",
            "type": "dimension"
          },
          "lg": {
            "value": "{component.menuItem.dimension.gap.md} + {component.menuItem.config.gap.step}",
            "type": "dimension"
          },
          "label": {
            "value": "0.25rem",
            "type": "dimension"
          }
        },
        "radius": {
          "sm": {
            "value": "{app.dimension.control.radius.sm}",
            "type": "dimension"
          },
          "md": {
            "value": "{app.dimension.control.radius.md}",
            "type": "dimension"
          },
          "lg": {
            "value": "{app.dimension.control.radius.lg}",
            "type": "dimension"
          }
        },
        "border": {
          "sm": {
            "value": "{app.dimension.control.border.sm}",
            "type": "dimension"
          },
          "md": {
            "value": "{app.dimension.control.border.md}",
            "type": "dimension"
          },
          "lg": {
            "value": "{app.dimension.control.border.lg}",
            "type": "dimension"
          }
        },
        "symbol": {
          "sm": {
            "value": "{component.menuItem.fontSize.symbol.sm}",
            "type": "dimension"
          },
          "md": {
            "value": "{component.menuItem.fontSize.symbol.md}",
            "type": "dimension"
          },
          "lg": {
            "value": "{component.menuItem.fontSize.symbol.lg}",
            "type": "dimension"
          }
        }
      },
      "fontSize": {
        "text": {
          "sm": {
            "value": "{component.menuItem.fontSize.text.md} - {component.menuItem.config.text.step}",
            "type": "fontSizes"
          },
          "md": {
            "value": "{component.menuItem.config.text.default}",
            "type": "fontSizes"
          },
          "lg": {
            "value": "{component.menuItem.fontSize.text.md} + {component.menuItem.config.text.step}",
            "type": "fontSizes"
          }
        },
        "symbol": {
          "sm": {
            "value": "{component.menuItem.fontSize.symbol.md} - {component.menuItem.config.symbol.default.step}",
            "type": "fontSizes"
          },
          "md": {
            "value": "{component.menuItem.config.symbol.default.default}",
            "type": "fontSizes"
          },
          "lg": {
            "value": "{component.menuItem.fontSize.symbol.md} + {component.menuItem.config.symbol.default.step}",
            "type": "fontSizes"
          }
        }
      },
      "letterSpacing": {
        "default": {
          "value": "{app.letterSpacing.control.text}",
          "type": "letterSpacing"
        }
      },
      "textCase": {
        "default": {
          "value": "{app.textCase.control.default}",
          "type": "textCase"
        }
      },
      "config": {
        "symbol": {
          "icon": {
            "step": {
              "value": "0.25rem",
              "type": "other"
            }
          },
          "default": {
            "default": {
              "value": "{app.fontSize.control.symbol.md}",
              "type": "other"
            },
            "step": {
              "value": "0.125rem",
              "type": "other"
            }
          }
        },
        "text": {
          "default": {
            "value": "{app.fontSize.control.text.md}",
            "type": "other"
          },
          "step": {
            "value": "0.0625rem",
            "type": "other"
          }
        },
        "gap": {
          "default": {
            "value": "{app.dimension.control.gap.lg}",
            "type": "other"
          },
          "step": {
            "value": "0.125rem",
            "type": "other"
          }
        }
      },
      "boxShadow": {
        "focusRing": {
          "value": "{app.boxShadow.focusRing.default.md}",
          "type": "boxShadow"
        }
      }
    }
  }
}