{
  "app": {
    "fontFamily": {
      "surface": {
        "title": {
          "$value": "Index",
          "$type": "fontFamily"
        },
        "callout": {
          "$value": "Index",
          "$type": "fontFamily"
        },
        "body": {
          "$value": "Index",
          "$type": "fontFamily"
        },
        "caption": {
          "$value": "Index",
          "$type": "fontFamily"
        },
        "footnote": {
          "$value": "Index",
          "$type": "fontFamily"
        }
      },
      "component": {
        "text": {
          "$value": "Index",
          "$type": "fontFamily"
        }
      }
    },
    "fontWeight": {
      "surface": {
        "callout": {
          "default": {
            "$value": "{config.fontWeight.medium}",
            "$type": "fontWeight"
          },
          "strong": {
            "$value": "{config.fontWeight.bold}",
            "$type": "fontWeight"
          }
        },
        "body": {
          "default": {
            "$value": "{config.fontWeight.medium}",
            "$type": "fontWeight"
          },
          "strong": {
            "$value": "{config.fontWeight.bold}",
            "$type": "fontWeight"
          }
        },
        "caption": {
          "default": {
            "$value": "{config.fontWeight.medium}",
            "$type": "fontWeight"
          },
          "strong": {
            "$value": "{config.fontWeight.semibold}",
            "$type": "fontWeight"
          }
        },
        "title": {
          "default": {
            "$value": "{config.fontWeight.semibold}",
            "$type": "fontWeight"
          },
          "strong": {
            "$value": "{config.fontWeight.bold}",
            "$type": "fontWeight"
          }
        },
        "footnote": {
          "default": {
            "$value": "{config.fontWeight.medium}",
            "$type": "fontWeight"
          },
          "strong": {
            "$value": "{config.fontWeight.semibold}",
            "$type": "fontWeight"
          }
        }
      }
    },
    "lineHeight": {
      "surface": {
        "title": {
          "sm": {
            "$value": "{app.lineHeight.surface.body.default}",
            "$type": "lineHeight"
          },
          "md": {
            "$value": "{app.lineHeight.surface.body.default}",
            "$type": "lineHeight"
          },
          "lg": {
            "$value": "{app.lineHeight.surface.body.default}",
            "$type": "lineHeight"
          }
        },
        "callout": {
          "default": {
            "$value": "{app.lineHeight.surface.body.default}",
            "$type": "lineHeight"
          },
          "short": {
            "$value": "{app.lineHeight.surface.body.short}",
            "$type": "lineHeight"
          }
        },
        "body": {
          "default": {
            "$value": "184%",
            "$type": "lineHeight"
          },
          "short": {
            "$value": "164%",
            "$type": "lineHeight"
          }
        },
        "footnote": {
          "default": {
            "$value": "{app.lineHeight.surface.body.short}",
            "$type": "lineHeight"
          }
        },
        "caption": {
          "default": {
            "$value": "{app.lineHeight.surface.body.short}",
            "$type": "lineHeight"
          }
        }
      }
    },
    "letterSpacing": {
      "surface": {
        "title": {
          "sm": {
            "$value": "0.0375rem",
            "$type": "letterSpacing"
          },
          "md": {
            "$value": "0.0375rem",
            "$type": "letterSpacing"
          },
          "lg": {
            "$value": "0.0375rem",
            "$type": "letterSpacing"
          }
        },
        "callout": {
          "sm": {
            "$value": "0.0375rem",
            "$type": "letterSpacing"
          },
          "md": {
            "$value": "0.0375rem",
            "$type": "letterSpacing"
          },
          "lg": {
            "$value": "0.0375rem",
            "$type": "letterSpacing"
          }
        }
      }
    }
  }
}
